pychessboard/__init__.py
pychessboard/additions.py
pychessboard/constants.py
pychessboard/pychessboard.py
pychessboard/assets/images/black bishop.png
pychessboard/assets/images/black king.png
pychessboard/assets/images/black knight.png
pychessboard/assets/images/black pawn.png
pychessboard/assets/images/black queen.png
pychessboard/assets/images/black rook.png
pychessboard/assets/images/white bishop.png
pychessboard/assets/images/white king.png
pychessboard/assets/images/white knight.png
pychessboard/assets/images/white pawn.png
pychessboard/assets/images/white queen.png
pychessboard/assets/images/white rook.png
pychessboard-2.8.6.dist-info/METADATA
pychessboard-2.8.6.dist-info/WHEEL
pychessboard-2.8.6.dist-info/top_level.txt
pychessboard-2.8.6.dist-info/RECORD
