Metadata-Version: 2.1
Name: pychessboard
Version: 2.8.6
Summary: a chessboard game
Home-page: https://github.com/nadernmds/pychessboard
Author: James gonzalez
Author-email: nadernmds@gmail.com
License: UNKNOWN
Platform: UNKNOWN
Requires-Dist: pygame
